{
    "1": {
        "count": 0,
        "average": 0
    },
    "2": {
        "count": 12050,
        "average": -0.9224896265560181
    },
    "3": {
        "count": 12233,
        "average": -0.9203793018883385
    },
    "4": {
        "count": 12524,
        "average": -0.9207920792079253
    },
    "5": {
        "count": 12562,
        "average": -0.9186435281006237
    },
    "6": {
        "count": 13022,
        "average": -0.9190600522193225
    },
    "7": {
        "count": 13203,
        "average": -0.9175944861016431
    },
    "8": {
        "count": 13390,
        "average": -0.909634055265122
    },
    "9": {
        "count": 13644,
        "average": -0.9055995309293412
    },
    "10": {
        "count": 13578,
        "average": -0.9136839004271633
    },
    "11": {
        "count": 14026,
        "average": -0.9131612719235731
    },
    "12": {
        "count": 14036,
        "average": -0.9048161869478467
    },
    "13": {
        "count": 14356,
        "average": -0.9070771802730597
    },
    "14": {
        "count": 14364,
        "average": -0.9026733500417727
    },
    "15": {
        "count": 14662,
        "average": -0.8985131632792274
    },
    "16": {
        "count": 14830,
        "average": -0.8980445043830069
    },
    "17": {
        "count": 14943,
        "average": -0.9063106471257426
    },
    "18": {
        "count": 15301,
        "average": -0.9054963727860924
    },
    "19": {
        "count": 15583,
        "average": -0.8966822819739443
    },
    "20": {
        "count": 15884,
        "average": -0.8936036262906071
    },
    "21": {
        "count": 15840,
        "average": -0.8958333333333329
    },
    "22": {
        "count": 16165,
        "average": -0.8916176925456235
    },
    "23": {
        "count": 16300,
        "average": -0.8934969325153367
    },
    "24": {
        "count": 16717,
        "average": -0.8998624155051695
    },
    "25": {
        "count": 17024,
        "average": -0.8874530075188006
    },
    "26": {
        "count": 17139,
        "average": -0.8933426687671387
    },
    "27": {
        "count": 17475,
        "average": -0.889327610872676
    },
    "28": {
        "count": 17649,
        "average": -0.8875856989064511
    },
    "29": {
        "count": 17550,
        "average": -0.8862678062678057
    },
    "30": {
        "count": 18014,
        "average": -0.8850893749306097
    },
    "31": {
        "count": 18188,
        "average": -0.8850890697162972
    },
    "32": {
        "count": 18515,
        "average": -0.8796651363759116
    },
    "33": {
        "count": 18548,
        "average": -0.8832219107181322
    },
    "34": {
        "count": 18766,
        "average": -0.8758392838111446
    },
    "35": {
        "count": 18916,
        "average": -0.8741805878621266
    },
    "36": {
        "count": 19433,
        "average": -0.8803066947975086
    },
    "37": {
        "count": 19683,
        "average": -0.8774577046181986
    },
    "38": {
        "count": 19681,
        "average": -0.8662669579797802
    },
    "39": {
        "count": 20056,
        "average": -0.8740526525728011
    },
    "40": {
        "count": 20064,
        "average": -0.8742025518341324
    },
    "41": {
        "count": 20468,
        "average": -0.8615399648231395
    },
    "42": {
        "count": 20655,
        "average": -0.8586298717017712
    },
    "43": {
        "count": 21033,
        "average": -0.8634526696144142
    },
    "44": {
        "count": 21346,
        "average": -0.8605827789749814
    },
    "45": {
        "count": 21628,
        "average": -0.8538931015350533
    },
    "46": {
        "count": 21705,
        "average": -0.8557935959456295
    },
    "47": {
        "count": 22103,
        "average": -0.8568520110392249
    },
    "48": {
        "count": 22127,
        "average": -0.8539341076512889
    },
    "49": {
        "count": 22425,
        "average": -0.8462430323299894
    },
    "50": {
        "count": 22708,
        "average": -0.8557336621454986
    },
    "51": {
        "count": 22862,
        "average": -0.8485696789432224
    },
    "52": {
        "count": 23121,
        "average": -0.8439513861857204
    },
    "53": {
        "count": 23466,
        "average": -0.8414727691127585
    },
    "54": {
        "count": 23768,
        "average": -0.8442443621676201
    },
    "55": {
        "count": 23892,
        "average": -0.8399464255817869
    },
    "56": {
        "count": 24038,
        "average": -0.8404193360512558
    },
    "57": {
        "count": 24340,
        "average": -0.8368940016433888
    },
    "58": {
        "count": 24837,
        "average": -0.8401578290453783
    },
    "59": {
        "count": 24865,
        "average": -0.8402573899054873
    },
    "60": {
        "count": 25337,
        "average": -0.83668153293602
    },
    "61": {
        "count": 25554,
        "average": -0.8342333881192737
    },
    "62": {
        "count": 25665,
        "average": -0.8315215273719048
    },
    "63": {
        "count": 25981,
        "average": -0.8273353604557196
    },
    "64": {
        "count": 26390,
        "average": -0.824933687002653
    },
    "65": {
        "count": 26522,
        "average": -0.8205263554784699
    },
    "66": {
        "count": 26567,
        "average": -0.8196258516204369
    },
    "67": {
        "count": 27282,
        "average": -0.823619969210469
    },
    "68": {
        "count": 27800,
        "average": -0.8187769784172648
    },
    "69": {
        "count": 27399,
        "average": -0.8230592357385316
    },
    "70": {
        "count": 28079,
        "average": -0.8182271448413383
    },
    "71": {
        "count": 28432,
        "average": -0.8121834552616756
    },
    "72": {
        "count": 28090,
        "average": -0.8104663581345678
    },
    "73": {
        "count": 28435,
        "average": -0.812414278178302
    },
    "74": {
        "count": 28779,
        "average": -0.808818930470133
    },
    "75": {
        "count": 29108,
        "average": -0.8071320599148003
    },
    "76": {
        "count": 29555,
        "average": -0.8032820165792635
    },
    "77": {
        "count": 29620,
        "average": -0.801282916948011
    },
    "78": {
        "count": 29879,
        "average": -0.8031393286254593
    },
    "79": {
        "count": 30175,
        "average": -0.8012924606462318
    },
    "80": {
        "count": 30643,
        "average": -0.8006069901771975
    },
    "81": {
        "count": 30996,
        "average": -0.7940379403794038
    },
    "82": {
        "count": 31581,
        "average": -0.7943067033976124
    },
    "83": {
        "count": 31494,
        "average": -0.7923413983615966
    },
    "84": {
        "count": 31791,
        "average": -0.791953697587376
    },
    "85": {
        "count": 32137,
        "average": -0.7886548215452558
    },
    "86": {
        "count": 32476,
        "average": -0.7898140165044967
    },
    "87": {
        "count": 32557,
        "average": -0.7792179869152619
    },
    "88": {
        "count": 32792,
        "average": -0.7779946328372876
    },
    "89": {
        "count": 33000,
        "average": -0.7791515151515167
    },
    "90": {
        "count": 33191,
        "average": -0.7718658672531702
    },
    "91": {
        "count": 33990,
        "average": -0.7753456899087988
    },
    "92": {
        "count": 34297,
        "average": -0.7714085780097433
    },
    "93": {
        "count": 34429,
        "average": -0.7710069999128567
    },
    "94": {
        "count": 34733,
        "average": -0.763567788558429
    },
    "95": {
        "count": 34811,
        "average": -0.7700152250725316
    },
    "96": {
        "count": 35301,
        "average": -0.7598368318177922
    },
    "97": {
        "count": 35499,
        "average": -0.7639370123102093
    },
    "98": {
        "count": 35656,
        "average": -0.7606013013237588
    },
    "99": {
        "count": 36451,
        "average": -0.7576472524759252
    },
    "100": {
        "count": 36460,
        "average": -0.7556226001097128
    },
    "101": {
        "count": 36871,
        "average": -0.7521087033169692
    },
    "102": {
        "count": 37031,
        "average": -0.7599308687316048
    },
    "103": {
        "count": 37435,
        "average": -0.7533324429010229
    },
    "104": {
        "count": 37451,
        "average": -0.7521027475901851
    },
    "105": {
        "count": 37690,
        "average": -0.7407269832846871
    },
    "106": {
        "count": 38174,
        "average": -0.7438046838162167
    },
    "107": {
        "count": 38258,
        "average": -0.7377803335250096
    },
    "108": {
        "count": 38595,
        "average": -0.7446301334369733
    },
    "109": {
        "count": 38882,
        "average": -0.7329355485828887
    },
    "110": {
        "count": 38898,
        "average": -0.7327883181654565
    },
    "111": {
        "count": 39251,
        "average": -0.7403887799037003
    },
    "112": {
        "count": 39608,
        "average": -0.7306099777822661
    },
    "113": {
        "count": 39912,
        "average": -0.7288033674082984
    },
    "114": {
        "count": 39897,
        "average": -0.7253928866832077
    },
    "115": {
        "count": 40842,
        "average": -0.7286127026100506
    },
    "116": {
        "count": 40431,
        "average": -0.7243699141747656
    },
    "117": {
        "count": 40548,
        "average": -0.7275821248890213
    },
    "118": {
        "count": 41156,
        "average": -0.7240256584702148
    },
    "119": {
        "count": 41091,
        "average": -0.7236864520211255
    },
    "120": {
        "count": 41867,
        "average": -0.7188238947142082
    },
    "121": {
        "count": 42202,
        "average": -0.7158902421686107
    },
    "122": {
        "count": 42361,
        "average": -0.7152569580510351
    },
    "123": {
        "count": 42375,
        "average": -0.71369911504425
    },
    "124": {
        "count": 42056,
        "average": -0.7120505992010713
    },
    "125": {
        "count": 42778,
        "average": -0.7109729300107486
    },
    "126": {
        "count": 43046,
        "average": -0.7117037587696801
    },
    "127": {
        "count": 43320,
        "average": -0.7059095106186444
    },
    "128": {
        "count": 43376,
        "average": -0.7091479158981958
    },
    "129": {
        "count": 43731,
        "average": -0.7053806224417435
    },
    "130": {
        "count": 44035,
        "average": -0.6987850573407469
    },
    "131": {
        "count": 44521,
        "average": -0.6941667976909688
    },
    "132": {
        "count": 44943,
        "average": -0.6943684222237025
    },
    "133": {
        "count": 45384,
        "average": -0.6946060285563265
    },
    "134": {
        "count": 44681,
        "average": -0.6960229180188459
    },
    "135": {
        "count": 45124,
        "average": -0.69151670951157
    },
    "136": {
        "count": 45679,
        "average": -0.6880404562271483
    },
    "137": {
        "count": 45700,
        "average": -0.6876586433260409
    },
    "138": {
        "count": 46383,
        "average": -0.6830735398745211
    },
    "139": {
        "count": 46806,
        "average": -0.6876468828782673
    },
    "140": {
        "count": 46825,
        "average": -0.6747463961558985
    },
    "141": {
        "count": 46929,
        "average": -0.6778963966843585
    },
    "142": {
        "count": 47320,
        "average": -0.6731191885038061
    },
    "143": {
        "count": 47392,
        "average": -0.6758946657663729
    },
    "144": {
        "count": 48015,
        "average": -0.673893574924503
    },
    "145": {
        "count": 48130,
        "average": -0.6735923540411387
    },
    "146": {
        "count": 48463,
        "average": -0.669025854775806
    },
    "147": {
        "count": 48529,
        "average": -0.6727317686331854
    },
    "148": {
        "count": 49093,
        "average": -0.6635772920782999
    },
    "149": {
        "count": 49108,
        "average": -0.6647389427384625
    },
    "150": {
        "count": 49368,
        "average": -0.6655323286339353
    },
    "151": {
        "count": 49411,
        "average": -0.666390075084494
    },
    "152": {
        "count": 49633,
        "average": -0.6664719037736972
    },
    "153": {
        "count": 49937,
        "average": -0.6563670224482816
    },
    "154": {
        "count": 50665,
        "average": -0.6558571005625192
    },
    "155": {
        "count": 50391,
        "average": -0.6511678672778822
    },
    "156": {
        "count": 50723,
        "average": -0.6449342507343746
    },
    "157": {
        "count": 51184,
        "average": -0.6560643951234759
    },
    "158": {
        "count": 51311,
        "average": -0.6490810937225888
    },
    "159": {
        "count": 52070,
        "average": -0.6466295371615204
    },
    "160": {
        "count": 51443,
        "average": -0.646754660498028
    },
    "161": {
        "count": 52186,
        "average": -0.643314298854094
    },
    "162": {
        "count": 52751,
        "average": -0.6410684157646294
    },
    "163": {
        "count": 52881,
        "average": -0.6384712845823588
    },
    "164": {
        "count": 52682,
        "average": -0.6333852169621486
    },
    "165": {
        "count": 53091,
        "average": -0.6388465088244675
    },
    "166": {
        "count": 53919,
        "average": -0.632189024277149
    },
    "167": {
        "count": 53626,
        "average": -0.6324917017864509
    },
    "168": {
        "count": 54607,
        "average": -0.6304869339095738
    },
    "169": {
        "count": 54126,
        "average": -0.6320807005875189
    },
    "170": {
        "count": 54598,
        "average": -0.6222205941609563
    },
    "171": {
        "count": 54952,
        "average": -0.6181758625709697
    },
    "172": {
        "count": 54978,
        "average": -0.620248099239694
    },
    "173": {
        "count": 55173,
        "average": -0.6241639932575771
    },
    "174": {
        "count": 55368,
        "average": -0.6216587198381732
    },
    "175": {
        "count": 56081,
        "average": -0.6147001658315752
    },
    "176": {
        "count": 56427,
        "average": -0.6083435234905277
    },
    "177": {
        "count": 56360,
        "average": -0.6052874378992145
    },
    "178": {
        "count": 56237,
        "average": -0.6104699752831776
    },
    "179": {
        "count": 56680,
        "average": -0.6099858856739588
    },
    "180": {
        "count": 57121,
        "average": -0.6081651231596018
    },
    "181": {
        "count": 57396,
        "average": -0.6035960694125064
    },
    "182": {
        "count": 57481,
        "average": -0.6086706911849121
    },
    "183": {
        "count": 57469,
        "average": -0.5993666150446346
    },
    "184": {
        "count": 57778,
        "average": -0.5940669458963667
    },
    "185": {
        "count": 58409,
        "average": -0.5998561865465896
    },
    "186": {
        "count": 58688,
        "average": -0.5959310250817885
    },
    "187": {
        "count": 58761,
        "average": -0.5915658344820508
    },
    "188": {
        "count": 58812,
        "average": -0.5955247228456716
    },
    "189": {
        "count": 58959,
        "average": -0.5879170270866164
    },
    "190": {
        "count": 59779,
        "average": -0.5856404422957938
    },
    "191": {
        "count": 60000,
        "average": -0.5808666666666602
    },
    "192": {
        "count": 60040,
        "average": -0.5913057961359169
    },
    "193": {
        "count": 60302,
        "average": -0.5806772578023958
    },
    "194": {
        "count": 60923,
        "average": -0.575858050325818
    },
    "195": {
        "count": 60816,
        "average": -0.5731057616416733
    },
    "196": {
        "count": 61374,
        "average": -0.5736305275849749
    },
    "197": {
        "count": 61567,
        "average": -0.5741549856254146
    },
    "198": {
        "count": 61460,
        "average": -0.5702570777741592
    },
    "199": {
        "count": 61628,
        "average": -0.5712014019601481
    },
    "200": {
        "count": 62088,
        "average": -0.5682257441051378
    },
    "201": {
        "count": 62540,
        "average": -0.5627758234729817
    },
    "202": {
        "count": 62587,
        "average": -0.5671625097863733
    },
    "203": {
        "count": 63153,
        "average": -0.5692999540797793
    },
    "204": {
        "count": 62931,
        "average": -0.5599942794489261
    },
    "205": {
        "count": 63092,
        "average": -0.5607050022189833
    },
    "206": {
        "count": 63147,
        "average": -0.5606125389963031
    },
    "207": {
        "count": 63964,
        "average": -0.5555937714964688
    },
    "208": {
        "count": 64118,
        "average": -0.5531987897314258
    },
    "209": {
        "count": 64277,
        "average": -0.5541484512345008
    },
    "210": {
        "count": 64600,
        "average": -0.5469040247677981
    },
    "211": {
        "count": 64753,
        "average": -0.5446697450311233
    },
    "212": {
        "count": 65196,
        "average": -0.5445119332474376
    },
    "213": {
        "count": 65459,
        "average": -0.5436227256756215
    },
    "214": {
        "count": 65365,
        "average": -0.5386521838904617
    },
    "215": {
        "count": 66134,
        "average": -0.5397828650920787
    },
    "216": {
        "count": 66217,
        "average": -0.5415678753190293
    },
    "217": {
        "count": 66489,
        "average": -0.539863736858719
    },
    "218": {
        "count": 67113,
        "average": -0.535380626704222
    },
    "219": {
        "count": 66819,
        "average": -0.5368083928223971
    },
    "220": {
        "count": 67007,
        "average": -0.5319294999029917
    },
    "221": {
        "count": 67348,
        "average": -0.5309140583239322
    },
    "222": {
        "count": 67741,
        "average": -0.528704920210814
    },
    "223": {
        "count": 67231,
        "average": -0.5230474037274438
    },
    "224": {
        "count": 68236,
        "average": -0.5206928893838992
    },
    "225": {
        "count": 68490,
        "average": -0.518791064388961
    },
    "226": {
        "count": 68915,
        "average": -0.5220198795617802
    },
    "227": {
        "count": 69012,
        "average": -0.5183446357155181
    },
    "228": {
        "count": 68888,
        "average": -0.5178550690976629
    },
    "229": {
        "count": 69703,
        "average": -0.5104945267779066
    },
    "230": {
        "count": 69528,
        "average": -0.5150442986997976
    },
    "231": {
        "count": 70216,
        "average": -0.5090007975390196
    },
    "232": {
        "count": 70115,
        "average": -0.5061826998502496
    },
    "233": {
        "count": 70532,
        "average": -0.5081381500595413
    },
    "234": {
        "count": 70897,
        "average": -0.5047181121909335
    },
    "235": {
        "count": 70980,
        "average": -0.49952099182868437
    },
    "236": {
        "count": 71228,
        "average": -0.5048295614084349
    },
    "237": {
        "count": 71052,
        "average": -0.5019422394865775
    },
    "238": {
        "count": 71679,
        "average": -0.5000488288062109
    },
    "239": {
        "count": 71985,
        "average": -0.4970063207612666
    },
    "240": {
        "count": 72015,
        "average": -0.49588280219398495
    },
    "241": {
        "count": 72146,
        "average": -0.4944695478612849
    },
    "242": {
        "count": 72841,
        "average": -0.49075383369255976
    },
    "243": {
        "count": 72993,
        "average": -0.4874303015357651
    },
    "244": {
        "count": 73037,
        "average": -0.48149568027164324
    },
    "245": {
        "count": 73747,
        "average": -0.4857553527601136
    },
    "246": {
        "count": 73383,
        "average": -0.479497976370551
    },
    "247": {
        "count": 73892,
        "average": -0.47745358090186096
    },
    "248": {
        "count": 74088,
        "average": -0.47934888241010515
    },
    "249": {
        "count": 73792,
        "average": -0.4778837814397239
    },
    "250": {
        "count": 74472,
        "average": -0.47166720378129007
    },
    "251": {
        "count": 74694,
        "average": -0.47409430476343306
    },
    "252": {
        "count": 74852,
        "average": -0.4704750708063908
    },
    "253": {
        "count": 75600,
        "average": -0.4721693121693095
    },
    "254": {
        "count": 75615,
        "average": -0.462461151887854
    },
    "255": {
        "count": 76077,
        "average": -0.4654100450859006
    },
    "256": {
        "count": 76316,
        "average": -0.4658000943445679
    },
    "257": {
        "count": 76621,
        "average": -0.4588428759739529
    },
    "258": {
        "count": 76862,
        "average": -0.458796284249693
    },
    "259": {
        "count": 77207,
        "average": -0.4554120740347367
    },
    "260": {
        "count": 76516,
        "average": -0.4544931778974331
    },
    "261": {
        "count": 77346,
        "average": -0.45359811754971147
    },
    "262": {
        "count": 77764,
        "average": -0.44768787613806116
    },
    "263": {
        "count": 78097,
        "average": -0.4479429427506845
    },
    "264": {
        "count": 77935,
        "average": -0.44415217809713253
    },
    "265": {
        "count": 78537,
        "average": -0.4479035359130113
    },
    "266": {
        "count": 78881,
        "average": -0.44716725193646145
    },
    "267": {
        "count": 78767,
        "average": -0.4447166960783064
    },
    "268": {
        "count": 79300,
        "average": -0.4371752837326585
    },
    "269": {
        "count": 79668,
        "average": -0.437917357031686
    },
    "270": {
        "count": 79745,
        "average": -0.4438773590820768
    },
    "271": {
        "count": 79734,
        "average": -0.4316351869967688
    },
    "272": {
        "count": 80276,
        "average": -0.43390303453086804
    },
    "273": {
        "count": 80101,
        "average": -0.43368996641739355
    },
    "274": {
        "count": 80477,
        "average": -0.4294767449084812
    },
    "275": {
        "count": 80794,
        "average": -0.42827437681015984
    },
    "276": {
        "count": 80586,
        "average": -0.4237460601097007
    },
    "277": {
        "count": 81290,
        "average": -0.4216508795669837
    },
    "278": {
        "count": 81314,
        "average": -0.4212804683080456
    },
    "279": {
        "count": 82113,
        "average": -0.4178997235516909
    },
    "280": {
        "count": 82280,
        "average": -0.4149003403014147
    },
    "281": {
        "count": 81984,
        "average": -0.41320257611241445
    },
    "282": {
        "count": 82741,
        "average": -0.4094826023374117
    },
    "283": {
        "count": 82305,
        "average": -0.41641455561630886
    },
    "284": {
        "count": 83400,
        "average": -0.41086330935251625
    },
    "285": {
        "count": 83154,
        "average": -0.4084229261370479
    },
    "286": {
        "count": 83280,
        "average": -0.4069884726224731
    },
    "287": {
        "count": 83387,
        "average": -0.4009138115053909
    },
    "288": {
        "count": 84027,
        "average": -0.40207314315636544
    },
    "289": {
        "count": 84271,
        "average": -0.3970642332474988
    },
    "290": {
        "count": 84746,
        "average": -0.4010336771057097
    },
    "291": {
        "count": 85099,
        "average": -0.39524553755038316
    },
    "292": {
        "count": 85150,
        "average": -0.3965707574867856
    },
    "293": {
        "count": 85227,
        "average": -0.3957079329320519
    },
    "294": {
        "count": 85812,
        "average": -0.3879177737379397
    },
    "295": {
        "count": 85747,
        "average": -0.3842583413996988
    },
    "296": {
        "count": 86198,
        "average": -0.38796723821898077
    },
    "297": {
        "count": 85623,
        "average": -0.3902105742615854
    },
    "298": {
        "count": 86313,
        "average": -0.3879485129702368
    },
    "299": {
        "count": 86760,
        "average": -0.38351775011525896
    },
    "300": {
        "count": 86394,
        "average": -0.3806977336389112
    },
    "301": {
        "count": 87335,
        "average": -0.38304230835289066
    },
    "302": {
        "count": 87562,
        "average": -0.3758708115392534
    },
    "303": {
        "count": 88136,
        "average": -0.374285195606791
    },
    "304": {
        "count": 87709,
        "average": -0.3761187563419963
    },
    "305": {
        "count": 88013,
        "average": -0.37107018281390647
    },
    "306": {
        "count": 88797,
        "average": -0.3697084360958107
    },
    "307": {
        "count": 88975,
        "average": -0.37065467828041415
    },
    "308": {
        "count": 88790,
        "average": -0.366415136839729
    },
    "309": {
        "count": 89419,
        "average": -0.36163455194086563
    },
    "310": {
        "count": 89722,
        "average": -0.35538663872851806
    },
    "311": {
        "count": 89693,
        "average": -0.35780941656539644
    },
    "312": {
        "count": 90163,
        "average": -0.35583332409081414
    },
    "313": {
        "count": 90416,
        "average": -0.35630861794372987
    },
    "314": {
        "count": 90601,
        "average": -0.3538923411441394
    },
    "315": {
        "count": 91053,
        "average": -0.35371706588470325
    },
    "316": {
        "count": 91059,
        "average": -0.3519146926717885
    },
    "317": {
        "count": 91559,
        "average": -0.3466289496390273
    },
    "318": {
        "count": 91631,
        "average": -0.3435845947332235
    },
    "319": {
        "count": 91448,
        "average": -0.34397690490771027
    },
    "320": {
        "count": 91440,
        "average": -0.3449693788276451
    },
    "321": {
        "count": 92888,
        "average": -0.34086211351304635
    },
    "322": {
        "count": 92516,
        "average": -0.33308833066712
    },
    "323": {
        "count": 92857,
        "average": -0.33659282552741987
    },
    "324": {
        "count": 92983,
        "average": -0.33435144058591265
    },
    "325": {
        "count": 93413,
        "average": -0.34131223705480074
    },
    "326": {
        "count": 93623,
        "average": -0.32736613866251124
    },
    "327": {
        "count": 94091,
        "average": -0.33028663740421754
    },
    "328": {
        "count": 94039,
        "average": -0.3274705175512277
    },
    "329": {
        "count": 94476,
        "average": -0.32410347601507683
    },
    "330": {
        "count": 94633,
        "average": -0.32357634229074234
    },
    "331": {
        "count": 95242,
        "average": -0.32439469981730445
    },
    "332": {
        "count": 95362,
        "average": -0.31826094251378984
    },
    "333": {
        "count": 95652,
        "average": -0.31447329904236127
    },
    "334": {
        "count": 95347,
        "average": -0.31691610643229123
    },
    "335": {
        "count": 95658,
        "average": -0.3115682953856414
    },
    "336": {
        "count": 95738,
        "average": -0.31055589212225426
    },
    "337": {
        "count": 96084,
        "average": -0.3118313142666876
    },
    "338": {
        "count": 97235,
        "average": -0.3027613513652477
    },
    "339": {
        "count": 96336,
        "average": -0.30393622321873665
    },
    "340": {
        "count": 96888,
        "average": -0.3039385682437461
    },
    "341": {
        "count": 96916,
        "average": -0.3035618473729862
    },
    "342": {
        "count": 97394,
        "average": -0.29743105324763613
    },
    "343": {
        "count": 97929,
        "average": -0.29936995169969943
    },
    "344": {
        "count": 97915,
        "average": -0.2936322320379967
    },
    "345": {
        "count": 98417,
        "average": -0.2946137354318845
    },
    "346": {
        "count": 98407,
        "average": -0.29931813793734163
    },
    "347": {
        "count": 99140,
        "average": -0.2938672584224333
    },
    "348": {
        "count": 99259,
        "average": -0.2894750098227888
    },
    "349": {
        "count": 99577,
        "average": -0.2879279351657491
    },
    "350": {
        "count": 99373,
        "average": -0.28491642599096895
    },
    "351": {
        "count": 99849,
        "average": -0.28494025979228116
    },
    "352": {
        "count": 100325,
        "average": -0.2805980563169739
    },
    "353": {
        "count": 99953,
        "average": -0.2764599361699979
    },
    "354": {
        "count": 100055,
        "average": -0.27521862975363504
    },
    "355": {
        "count": 100287,
        "average": -0.27456200703979905
    },
    "356": {
        "count": 101198,
        "average": -0.2753018834364281
    },
    "357": {
        "count": 101349,
        "average": -0.2721388469545853
    },
    "358": {
        "count": 101711,
        "average": -0.2676308363893771
    },
    "359": {
        "count": 101580,
        "average": -0.2699744044103188
    },
    "360": {
        "count": 102404,
        "average": -0.26850513651810154
    },
    "361": {
        "count": 102107,
        "average": -0.26655371326157923
    },
    "362": {
        "count": 101888,
        "average": -0.25938285175878817
    },
    "363": {
        "count": 102345,
        "average": -0.26065757975474924
    },
    "364": {
        "count": 102712,
        "average": -0.25928810655035567
    },
    "365": {
        "count": 102411,
        "average": -0.25482614172305945
    },
    "366": {
        "count": 102712,
        "average": -0.2536801931614594
    },
    "367": {
        "count": 103361,
        "average": -0.24915587116997648
    },
    "368": {
        "count": 103694,
        "average": -0.24921403359886202
    },
    "369": {
        "count": 104313,
        "average": -0.24831996012002278
    },
    "370": {
        "count": 104350,
        "average": -0.24766650694777406
    },
    "371": {
        "count": 103969,
        "average": -0.24956477411536188
    },
    "372": {
        "count": 104147,
        "average": -0.2452591049190069
    },
    "373": {
        "count": 104393,
        "average": -0.2422480434511914
    },
    "374": {
        "count": 104686,
        "average": -0.2461074069120977
    },
    "375": {
        "count": 105255,
        "average": -0.2360837964942291
    },
    "376": {
        "count": 105214,
        "average": -0.23601421864010516
    },
    "377": {
        "count": 105569,
        "average": -0.23155471776752534
    },
    "378": {
        "count": 106043,
        "average": -0.23546108654036382
    },
    "379": {
        "count": 106121,
        "average": -0.22878600842434715
    },
    "380": {
        "count": 106248,
        "average": -0.22893607409080424
    },
    "381": {
        "count": 107040,
        "average": -0.22793348281016218
    },
    "382": {
        "count": 106982,
        "average": -0.22628105662635095
    },
    "383": {
        "count": 106941,
        "average": -0.2194948616526879
    },
    "384": {
        "count": 107643,
        "average": -0.22438059139934674
    },
    "385": {
        "count": 107431,
        "average": -0.2213048375236215
    },
    "386": {
        "count": 107484,
        "average": -0.21623683524989654
    },
    "387": {
        "count": 107962,
        "average": -0.21642800244530322
    },
    "388": {
        "count": 107593,
        "average": -0.21623153922652968
    },
    "389": {
        "count": 108304,
        "average": -0.21352858620180323
    },
    "390": {
        "count": 108449,
        "average": -0.20587557284990943
    },
    "391": {
        "count": 108358,
        "average": -0.20899241403495594
    },
    "392": {
        "count": 108838,
        "average": -0.20457928297102101
    },
    "393": {
        "count": 109018,
        "average": -0.20259039791594208
    },
    "394": {
        "count": 109117,
        "average": -0.20129768963589392
    },
    "395": {
        "count": 109463,
        "average": -0.19446753697596558
    },
    "396": {
        "count": 109610,
        "average": -0.19326703767904235
    },
    "397": {
        "count": 109296,
        "average": -0.19728077880251896
    },
    "398": {
        "count": 110041,
        "average": -0.1974445888350699
    },
    "399": {
        "count": 109783,
        "average": -0.1966697940482582
    },
    "400": {
        "count": 114712,
        "average": -0.18683311249041143
    },
    "401": {
        "count": 114833,
        "average": -0.18511229350448286
    },
    "402": {
        "count": 115192,
        "average": -0.1883811375789987
    },
    "403": {
        "count": 114880,
        "average": -0.18147632311977663
    },
    "404": {
        "count": 116011,
        "average": -0.1831636655144803
    },
    "405": {
        "count": 115236,
        "average": -0.1823909195043227
    },
    "406": {
        "count": 115604,
        "average": -0.17703539669907767
    },
    "407": {
        "count": 115890,
        "average": -0.1777547674518942
    },
    "408": {
        "count": 116660,
        "average": -0.1755357448997085
    },
    "409": {
        "count": 116437,
        "average": -0.1757946357257583
    },
    "410": {
        "count": 116607,
        "average": -0.1757784695601464
    },
    "411": {
        "count": 116143,
        "average": -0.17171073590315244
    },
    "412": {
        "count": 116647,
        "average": -0.16639090589556296
    },
    "413": {
        "count": 116843,
        "average": -0.16362982805987802
    },
    "414": {
        "count": 117168,
        "average": -0.16443056124539224
    },
    "415": {
        "count": 117264,
        "average": -0.16270978305362205
    },
    "416": {
        "count": 117553,
        "average": -0.15837111770860918
    },
    "417": {
        "count": 117398,
        "average": -0.15896352578408915
    },
    "418": {
        "count": 117628,
        "average": -0.16150916448464653
    },
    "419": {
        "count": 118143,
        "average": -0.1547362095088164
    },
    "420": {
        "count": 117937,
        "average": -0.15137743032297024
    },
    "421": {
        "count": 118112,
        "average": -0.15199133026280204
    },
    "422": {
        "count": 118267,
        "average": -0.14804636965510024
    },
    "423": {
        "count": 118708,
        "average": -0.1456178185126497
    },
    "424": {
        "count": 119364,
        "average": -0.14714654334640132
    },
    "425": {
        "count": 119499,
        "average": -0.13763295090335656
    },
    "426": {
        "count": 118568,
        "average": -0.14153903245394928
    },
    "427": {
        "count": 119083,
        "average": -0.13577924640796832
    },
    "428": {
        "count": 120004,
        "average": -0.1365954468184391
    },
    "429": {
        "count": 119472,
        "average": -0.13794027052363753
    },
    "430": {
        "count": 119317,
        "average": -0.13764174426108647
    },
    "431": {
        "count": 120247,
        "average": -0.13360000665297325
    },
    "432": {
        "count": 119951,
        "average": -0.13162874840560176
    },
    "433": {
        "count": 120231,
        "average": -0.12762931357137253
    },
    "434": {
        "count": 119864,
        "average": -0.12554228125208586
    },
    "435": {
        "count": 120494,
        "average": -0.12365760950752633
    },
    "436": {
        "count": 120376,
        "average": -0.12163554196849984
    },
    "437": {
        "count": 120921,
        "average": -0.12483356902440411
    },
    "438": {
        "count": 120973,
        "average": -0.11277723128301473
    },
    "439": {
        "count": 120992,
        "average": -0.11597460989156302
    },
    "440": {
        "count": 120392,
        "average": -0.11203402219416463
    },
    "441": {
        "count": 121289,
        "average": -0.11162595124042457
    },
    "442": {
        "count": 121472,
        "average": -0.11074157007376217
    },
    "443": {
        "count": 121065,
        "average": -0.11184900673192179
    },
    "444": {
        "count": 121034,
        "average": -0.10580498041872548
    },
    "445": {
        "count": 121757,
        "average": -0.11131187529259047
    },
    "446": {
        "count": 121826,
        "average": -0.10557680626467207
    },
    "447": {
        "count": 122334,
        "average": -0.09810845717462009
    },
    "448": {
        "count": 121933,
        "average": -0.09799644066823647
    },
    "449": {
        "count": 121771,
        "average": -0.09949002636095733
    },
    "450": {
        "count": 122470,
        "average": -0.0928880542173593
    },
    "451": {
        "count": 122365,
        "average": -0.09688227842929029
    },
    "452": {
        "count": 122693,
        "average": -0.09024964749415264
    },
    "453": {
        "count": 122594,
        "average": -0.08882979591170799
    },
    "454": {
        "count": 122654,
        "average": -0.08875373000472882
    },
    "455": {
        "count": 123323,
        "average": -0.08644778346293673
    },
    "456": {
        "count": 123089,
        "average": -0.0814126363850558
    },
    "457": {
        "count": 123278,
        "average": -0.08372945699962736
    },
    "458": {
        "count": 122868,
        "average": -0.08256014584757573
    },
    "459": {
        "count": 123025,
        "average": -0.07165210323105067
    },
    "460": {
        "count": 123722,
        "average": -0.07615460467823079
    },
    "461": {
        "count": 123831,
        "average": -0.07580492768369762
    },
    "462": {
        "count": 123801,
        "average": -0.07527402848119115
    },
    "463": {
        "count": 123809,
        "average": -0.07449377670443996
    },
    "464": {
        "count": 123028,
        "average": -0.06751308645186431
    },
    "465": {
        "count": 124196,
        "average": -0.07244999838964218
    },
    "466": {
        "count": 124284,
        "average": -0.07075729780180824
    },
    "467": {
        "count": 123826,
        "average": -0.06344386477799448
    },
    "468": {
        "count": 124276,
        "average": -0.06158872187711197
    },
    "469": {
        "count": 124468,
        "average": -0.06277918822508585
    },
    "470": {
        "count": 124486,
        "average": -0.05753257394405824
    },
    "471": {
        "count": 124577,
        "average": -0.05431981826500894
    },
    "472": {
        "count": 123994,
        "average": -0.054873622917237776
    },
    "473": {
        "count": 124375,
        "average": -0.055774874371859344
    },
    "474": {
        "count": 124202,
        "average": -0.052028147694884265
    },
    "475": {
        "count": 124655,
        "average": -0.04998596125305885
    },
    "476": {
        "count": 124314,
        "average": -0.052077802982769206
    },
    "477": {
        "count": 124520,
        "average": -0.04460327658207506
    },
    "478": {
        "count": 124886,
        "average": -0.0401646301426898
    },
    "479": {
        "count": 125181,
        "average": -0.04225082081146511
    },
    "480": {
        "count": 124984,
        "average": -0.04061319848940742
    },
    "481": {
        "count": 125162,
        "average": -0.036992058292453125
    },
    "482": {
        "count": 124809,
        "average": -0.03625539824852382
    },
    "483": {
        "count": 125345,
        "average": -0.033946308189396486
    },
    "484": {
        "count": 124744,
        "average": -0.032402360033348
    },
    "485": {
        "count": 125571,
        "average": -0.02717984247955345
    },
    "486": {
        "count": 124589,
        "average": -0.026559327067397862
    },
    "487": {
        "count": 124995,
        "average": -0.02744909796391872
    },
    "488": {
        "count": 125054,
        "average": -0.0280838677691237
    },
    "489": {
        "count": 125422,
        "average": -0.019900814849069155
    },
    "490": {
        "count": 125396,
        "average": -0.026842961497974247
    },
    "491": {
        "count": 125521,
        "average": -0.020036487918356313
    },
    "492": {
        "count": 125572,
        "average": -0.019048832542286287
    },
    "493": {
        "count": 125876,
        "average": -0.013648352346754036
    },
    "494": {
        "count": 124991,
        "average": -0.014473042059028126
    },
    "495": {
        "count": 125580,
        "average": -0.013919413919413991
    },
    "496": {
        "count": 125988,
        "average": -0.009969203416198327
    },
    "497": {
        "count": 125311,
        "average": -0.011834555625603425
    },
    "498": {
        "count": 125172,
        "average": -0.00989039082222858
    },
    "499": {
        "count": 125133,
        "average": -0.0032205733099981955
    },
    "500": {
        "count": 1000000,
        "average": -0.0025639999999999474
    },
    "501": {
        "count": 125639,
        "average": -0.000963076751645596
    },
    "502": {
        "count": 125646,
        "average": -0.0010505706508762917
    },
    "503": {
        "count": 126028,
        "average": 0.005728885644459922
    },
    "504": {
        "count": 125175,
        "average": 0.005344517675254718
    },
    "505": {
        "count": 125479,
        "average": 0.00816869755098457
    },
    "506": {
        "count": 125911,
        "average": 0.011714623821588265
    },
    "507": {
        "count": 125438,
        "average": 0.012149428402876226
    },
    "508": {
        "count": 125650,
        "average": 0.015280541185833708
    },
    "509": {
        "count": 125140,
        "average": 0.013696659741089813
    },
    "510": {
        "count": 125800,
        "average": 0.01947535771065179
    },
    "511": {
        "count": 125173,
        "average": 0.02041175013780942
    },
    "512": {
        "count": 125296,
        "average": 0.02284191035627604
    },
    "513": {
        "count": 125073,
        "average": 0.02004429413222708
    },
    "514": {
        "count": 125425,
        "average": 0.020689655172413706
    },
    "515": {
        "count": 125085,
        "average": 0.02827677179517903
    },
    "516": {
        "count": 125563,
        "average": 0.030813217269418554
    },
    "517": {
        "count": 124587,
        "average": 0.03172883206113015
    },
    "518": {
        "count": 125234,
        "average": 0.032387370841784086
    },
    "519": {
        "count": 125075,
        "average": 0.027351589046572096
    },
    "520": {
        "count": 124898,
        "average": 0.035709138657144444
    },
    "521": {
        "count": 124375,
        "average": 0.03847236180904517
    },
    "522": {
        "count": 124569,
        "average": 0.039632653388885046
    },
    "523": {
        "count": 125454,
        "average": 0.036172621040382644
    },
    "524": {
        "count": 124391,
        "average": 0.04423953501459103
    },
    "525": {
        "count": 124059,
        "average": 0.04264906213978786
    },
    "526": {
        "count": 124366,
        "average": 0.04250357814836829
    },
    "527": {
        "count": 124691,
        "average": 0.04633052906785589
    },
    "528": {
        "count": 123986,
        "average": 0.0495862436081497
    },
    "529": {
        "count": 124010,
        "average": 0.049270220143537026
    },
    "530": {
        "count": 124322,
        "average": 0.0489213493991419
    },
    "531": {
        "count": 123803,
        "average": 0.06137977270340716
    },
    "532": {
        "count": 124411,
        "average": 0.05812187025263144
    },
    "533": {
        "count": 124321,
        "average": 0.059692248292725555
    },
    "534": {
        "count": 123770,
        "average": 0.06237375777652062
    },
    "535": {
        "count": 123470,
        "average": 0.06866445290353958
    },
    "536": {
        "count": 123403,
        "average": 0.0678670696822618
    },
    "537": {
        "count": 123170,
        "average": 0.0690103109523434
    },
    "538": {
        "count": 123637,
        "average": 0.07008419809603882
    },
    "539": {
        "count": 123241,
        "average": 0.0720620572699015
    },
    "540": {
        "count": 123325,
        "average": 0.07489965538211905
    },
    "541": {
        "count": 123048,
        "average": 0.07575905337754281
    },
    "542": {
        "count": 122669,
        "average": 0.08278375139603183
    },
    "543": {
        "count": 123492,
        "average": 0.07900106889515116
    },
    "544": {
        "count": 122854,
        "average": 0.08414866426815512
    },
    "545": {
        "count": 122706,
        "average": 0.08535849917689468
    },
    "546": {
        "count": 122773,
        "average": 0.08540151336205823
    },
    "547": {
        "count": 122593,
        "average": 0.08784351471943733
    },
    "548": {
        "count": 123069,
        "average": 0.09441045267289125
    },
    "549": {
        "count": 122074,
        "average": 0.09022396251453957
    },
    "550": {
        "count": 122664,
        "average": 0.09202373964651345
    },
    "551": {
        "count": 122302,
        "average": 0.09178917760952443
    },
    "552": {
        "count": 122531,
        "average": 0.09825268707510722
    },
    "553": {
        "count": 122836,
        "average": 0.10322706698362102
    },
    "554": {
        "count": 122199,
        "average": 0.09799589194674219
    },
    "555": {
        "count": 121614,
        "average": 0.10160014472017932
    },
    "556": {
        "count": 121099,
        "average": 0.10341125855704887
    },
    "557": {
        "count": 121245,
        "average": 0.10368262608767453
    },
    "558": {
        "count": 121527,
        "average": 0.10464341257498343
    },
    "559": {
        "count": 121068,
        "average": 0.11436548055638265
    },
    "560": {
        "count": 121539,
        "average": 0.11544442524621784
    },
    "561": {
        "count": 120545,
        "average": 0.11639636650213539
    },
    "562": {
        "count": 120326,
        "average": 0.11563585592473881
    },
    "563": {
        "count": 121087,
        "average": 0.1183694368511905
    },
    "564": {
        "count": 120713,
        "average": 0.11984624688310198
    },
    "565": {
        "count": 120610,
        "average": 0.11879611972473057
    },
    "566": {
        "count": 120447,
        "average": 0.12256843258860632
    },
    "567": {
        "count": 119559,
        "average": 0.12930017815471784
    },
    "568": {
        "count": 119709,
        "average": 0.12806890041684688
    },
    "569": {
        "count": 120127,
        "average": 0.12619144738485047
    },
    "570": {
        "count": 119579,
        "average": 0.13006464345746144
    },
    "571": {
        "count": 119733,
        "average": 0.12628932708609955
    },
    "572": {
        "count": 119240,
        "average": 0.13396511237839526
    },
    "573": {
        "count": 118930,
        "average": 0.14231901118304657
    },
    "574": {
        "count": 119716,
        "average": 0.13580473787964792
    },
    "575": {
        "count": 118797,
        "average": 0.13758764951976787
    },
    "576": {
        "count": 118719,
        "average": 0.14109788660618722
    },
    "577": {
        "count": 118449,
        "average": 0.1408285422418104
    },
    "578": {
        "count": 118378,
        "average": 0.1468854010035649
    },
    "579": {
        "count": 118343,
        "average": 0.14541628993687652
    },
    "580": {
        "count": 118510,
        "average": 0.1486288076955557
    },
    "581": {
        "count": 118139,
        "average": 0.15313317363444795
    },
    "582": {
        "count": 117175,
        "average": 0.1527885641135023
    },
    "583": {
        "count": 117355,
        "average": 0.15340633121724398
    },
    "584": {
        "count": 117315,
        "average": 0.15680006819247475
    },
    "585": {
        "count": 117348,
        "average": 0.15872447762211472
    },
    "586": {
        "count": 116958,
        "average": 0.16221207612989214
    },
    "587": {
        "count": 117176,
        "average": 0.16209804055438007
    },
    "588": {
        "count": 116788,
        "average": 0.16368120012330473
    },
    "589": {
        "count": 116586,
        "average": 0.1680990856535091
    },
    "590": {
        "count": 116461,
        "average": 0.1646302195584802
    },
    "591": {
        "count": 116191,
        "average": 0.16907505744851253
    },
    "592": {
        "count": 116400,
        "average": 0.1724742268041231
    },
    "593": {
        "count": 115601,
        "average": 0.1721351891419645
    },
    "594": {
        "count": 115449,
        "average": 0.1771951251201839
    },
    "595": {
        "count": 115367,
        "average": 0.18227916128529215
    },
    "596": {
        "count": 115355,
        "average": 0.18023492696458554
    },
    "597": {
        "count": 115521,
        "average": 0.18072038850079464
    },
    "598": {
        "count": 114859,
        "average": 0.18256296850921735
    },
    "599": {
        "count": 114336,
        "average": 0.18249720123145613
    },
    "600": {
        "count": 114545,
        "average": 0.18882535248155638
    },
    "601": {
        "count": 109801,
        "average": 0.18747552390233294
    },
    "602": {
        "count": 109783,
        "average": 0.19078545858648224
    },
    "603": {
        "count": 109810,
        "average": 0.1905108824332943
    },
    "604": {
        "count": 109138,
        "average": 0.1931866077809756
    },
    "605": {
        "count": 108732,
        "average": 0.19685097303461602
    },
    "606": {
        "count": 108823,
        "average": 0.19877231835181874
    },
    "607": {
        "count": 108840,
        "average": 0.20077177508268992
    },
    "608": {
        "count": 108895,
        "average": 0.19932044630148496
    },
    "609": {
        "count": 108227,
        "average": 0.20886654901272378
    },
    "610": {
        "count": 108254,
        "average": 0.20370609861991343
    },
    "611": {
        "count": 108286,
        "average": 0.20774615370408206
    },
    "612": {
        "count": 107943,
        "average": 0.21058336344181874
    },
    "613": {
        "count": 107620,
        "average": 0.20771232112990096
    },
    "614": {
        "count": 107669,
        "average": 0.21782500069657773
    },
    "615": {
        "count": 106731,
        "average": 0.21677863038854872
    },
    "616": {
        "count": 107101,
        "average": 0.21959645568202252
    },
    "617": {
        "count": 107200,
        "average": 0.2247574626865669
    },
    "618": {
        "count": 106540,
        "average": 0.21496151680120085
    },
    "619": {
        "count": 106747,
        "average": 0.21811385800069455
    },
    "620": {
        "count": 106168,
        "average": 0.22609449174892693
    },
    "621": {
        "count": 105493,
        "average": 0.2277591878134105
    },
    "622": {
        "count": 106160,
        "average": 0.22733609645817618
    },
    "623": {
        "count": 105617,
        "average": 0.22618517852239758
    },
    "624": {
        "count": 105653,
        "average": 0.2374660445041786
    },
    "625": {
        "count": 105512,
        "average": 0.23790658882401902
    },
    "626": {
        "count": 104540,
        "average": 0.23663669408838583
    },
    "627": {
        "count": 104397,
        "average": 0.24015057903962894
    },
    "628": {
        "count": 104597,
        "average": 0.24080040536535513
    },
    "629": {
        "count": 104388,
        "average": 0.24878338506341688
    },
    "630": {
        "count": 103598,
        "average": 0.2479005386204378
    },
    "631": {
        "count": 103503,
        "average": 0.25107484807203423
    },
    "632": {
        "count": 103526,
        "average": 0.2556072870583273
    },
    "633": {
        "count": 103279,
        "average": 0.24941178748826184
    },
    "634": {
        "count": 103242,
        "average": 0.25179674938494045
    },
    "635": {
        "count": 102782,
        "average": 0.25245665583468174
    },
    "636": {
        "count": 102514,
        "average": 0.25875490176951194
    },
    "637": {
        "count": 101974,
        "average": 0.2599486143526772
    },
    "638": {
        "count": 102664,
        "average": 0.2543637497077843
    },
    "639": {
        "count": 101847,
        "average": 0.2655846514870343
    },
    "640": {
        "count": 101910,
        "average": 0.2627023844568741
    },
    "641": {
        "count": 101015,
        "average": 0.2624857694401829
    },
    "642": {
        "count": 101194,
        "average": 0.26655730576911874
    },
    "643": {
        "count": 101164,
        "average": 0.2676446166620566
    },
    "644": {
        "count": 100286,
        "average": 0.26948926071435636
    },
    "645": {
        "count": 100623,
        "average": 0.26921280422965554
    },
    "646": {
        "count": 100318,
        "average": 0.26952291712354853
    },
    "647": {
        "count": 100692,
        "average": 0.28105509871688256
    },
    "648": {
        "count": 99904,
        "average": 0.2766655989750169
    },
    "649": {
        "count": 99326,
        "average": 0.27185228439683723
    },
    "650": {
        "count": 99108,
        "average": 0.28171287887960444
    },
    "651": {
        "count": 99274,
        "average": 0.28259161512581626
    },
    "652": {
        "count": 98763,
        "average": 0.28414487206748235
    },
    "653": {
        "count": 98738,
        "average": 0.28499665782170513
    },
    "654": {
        "count": 98208,
        "average": 0.2848647768002658
    },
    "655": {
        "count": 98396,
        "average": 0.2908654823366808
    },
    "656": {
        "count": 97428,
        "average": 0.2875969947037811
    },
    "657": {
        "count": 97956,
        "average": 0.29886887990526484
    },
    "658": {
        "count": 97802,
        "average": 0.2999529661970094
    },
    "659": {
        "count": 97344,
        "average": 0.30152859960552386
    },
    "660": {
        "count": 97053,
        "average": 0.3021751002029824
    },
    "661": {
        "count": 96774,
        "average": 0.3011346022692053
    },
    "662": {
        "count": 96620,
        "average": 0.2988615193541718
    },
    "663": {
        "count": 96142,
        "average": 0.30690021010588553
    },
    "664": {
        "count": 95948,
        "average": 0.3108558802684837
    },
    "665": {
        "count": 95746,
        "average": 0.31449877801683174
    },
    "666": {
        "count": 95361,
        "average": 0.311039104036243
    },
    "667": {
        "count": 95639,
        "average": 0.31348090214243385
    },
    "668": {
        "count": 94914,
        "average": 0.3204163769306962
    },
    "669": {
        "count": 93969,
        "average": 0.31434834892358043
    },
    "670": {
        "count": 94650,
        "average": 0.31936608557844764
    },
    "671": {
        "count": 94182,
        "average": 0.32454184451381235
    },
    "672": {
        "count": 93654,
        "average": 0.3235526512482133
    },
    "673": {
        "count": 93786,
        "average": 0.3246966498198007
    },
    "674": {
        "count": 93790,
        "average": 0.3256210683441756
    },
    "675": {
        "count": 92821,
        "average": 0.3316598614537672
    },
    "676": {
        "count": 93377,
        "average": 0.3319982436788517
    },
    "677": {
        "count": 92139,
        "average": 0.33101075548899267
    },
    "678": {
        "count": 92444,
        "average": 0.33587901864912806
    },
    "679": {
        "count": 92123,
        "average": 0.3373858862607617
    },
    "680": {
        "count": 91753,
        "average": 0.3414929212123857
    },
    "681": {
        "count": 92111,
        "average": 0.34409571061002575
    },
    "682": {
        "count": 91059,
        "average": 0.3403397797032685
    },
    "683": {
        "count": 91102,
        "average": 0.34657856029505085
    },
    "684": {
        "count": 90995,
        "average": 0.34534864552997246
    },
    "685": {
        "count": 90525,
        "average": 0.3475835404584341
    },
    "686": {
        "count": 90759,
        "average": 0.34908934651108514
    },
    "687": {
        "count": 90261,
        "average": 0.3497080688226351
    },
    "688": {
        "count": 89750,
        "average": 0.35425069637883083
    },
    "689": {
        "count": 89455,
        "average": 0.3518081717064427
    },
    "690": {
        "count": 88916,
        "average": 0.3581132754509855
    },
    "691": {
        "count": 89029,
        "average": 0.36200563861213336
    },
    "692": {
        "count": 88738,
        "average": 0.3607248303996044
    },
    "693": {
        "count": 88547,
        "average": 0.358171366618859
    },
    "694": {
        "count": 88897,
        "average": 0.36477046469509206
    },
    "695": {
        "count": 87981,
        "average": 0.36786351598640626
    },
    "696": {
        "count": 88135,
        "average": 0.3723492369660178
    },
    "697": {
        "count": 88165,
        "average": 0.3737197300516065
    },
    "698": {
        "count": 87418,
        "average": 0.3739275664050883
    },
    "699": {
        "count": 86673,
        "average": 0.37756856229736585
    },
    "700": {
        "count": 86661,
        "average": 0.3782208836731662
    },
    "701": {
        "count": 86481,
        "average": 0.3806500849897641
    },
    "702": {
        "count": 86518,
        "average": 0.3802214568066793
    },
    "703": {
        "count": 86344,
        "average": 0.38814509404243686
    },
    "704": {
        "count": 85731,
        "average": 0.38283701344904664
    },
    "705": {
        "count": 85806,
        "average": 0.3833531454676786
    },
    "706": {
        "count": 85493,
        "average": 0.3899149637982038
    },
    "707": {
        "count": 84917,
        "average": 0.3929601846508944
    },
    "708": {
        "count": 84767,
        "average": 0.3897861195984258
    },
    "709": {
        "count": 84837,
        "average": 0.39158621827739964
    },
    "710": {
        "count": 84400,
        "average": 0.3936492890995271
    },
    "711": {
        "count": 83875,
        "average": 0.3918569299552915
    },
    "712": {
        "count": 83767,
        "average": 0.3975670610144773
    },
    "713": {
        "count": 84485,
        "average": 0.40803692963247873
    },
    "714": {
        "count": 83352,
        "average": 0.4037335636817328
    },
    "715": {
        "count": 83127,
        "average": 0.4107810939887179
    },
    "716": {
        "count": 82900,
        "average": 0.4089505428226767
    },
    "717": {
        "count": 82630,
        "average": 0.4121263463633039
    },
    "718": {
        "count": 82439,
        "average": 0.4054513033879588
    },
    "719": {
        "count": 81890,
        "average": 0.4118940041519079
    },
    "720": {
        "count": 82259,
        "average": 0.4187140616832223
    },
    "721": {
        "count": 81776,
        "average": 0.4182645274897273
    },
    "722": {
        "count": 81435,
        "average": 0.42054399214097404
    },
    "723": {
        "count": 81511,
        "average": 0.415416324177104
    },
    "724": {
        "count": 80540,
        "average": 0.42381425378693977
    },
    "725": {
        "count": 80810,
        "average": 0.42408117807201806
    },
    "726": {
        "count": 80816,
        "average": 0.4210304890120753
    },
    "727": {
        "count": 79975,
        "average": 0.4305970615817464
    },
    "728": {
        "count": 79908,
        "average": 0.43642689092456555
    },
    "729": {
        "count": 78961,
        "average": 0.43121287724319646
    },
    "730": {
        "count": 79753,
        "average": 0.43558236053815697
    },
    "731": {
        "count": 79302,
        "average": 0.43504577438147835
    },
    "732": {
        "count": 78595,
        "average": 0.43400979706088116
    },
    "733": {
        "count": 78719,
        "average": 0.4385345342293412
    },
    "734": {
        "count": 78588,
        "average": 0.4331450094161921
    },
    "735": {
        "count": 78297,
        "average": 0.437807323396812
    },
    "736": {
        "count": 77707,
        "average": 0.4440655282020968
    },
    "737": {
        "count": 77661,
        "average": 0.4442512973049513
    },
    "738": {
        "count": 77330,
        "average": 0.44795034268718514
    },
    "739": {
        "count": 77205,
        "average": 0.4541027135548207
    },
    "740": {
        "count": 76953,
        "average": 0.45356256416253876
    },
    "741": {
        "count": 76845,
        "average": 0.4552150432689199
    },
    "742": {
        "count": 76468,
        "average": 0.45713239525029936
    },
    "743": {
        "count": 76365,
        "average": 0.45873109408760815
    },
    "744": {
        "count": 76210,
        "average": 0.45896863928618353
    },
    "745": {
        "count": 75784,
        "average": 0.4661406101551804
    },
    "746": {
        "count": 75741,
        "average": 0.4649397288126692
    },
    "747": {
        "count": 75496,
        "average": 0.4632033485217783
    },
    "748": {
        "count": 74763,
        "average": 0.4690956756684454
    },
    "749": {
        "count": 74882,
        "average": 0.4664672417937525
    },
    "750": {
        "count": 74922,
        "average": 0.46365553508982754
    },
    "751": {
        "count": 74755,
        "average": 0.46721958397431745
    },
    "752": {
        "count": 73675,
        "average": 0.4770274855785552
    },
    "753": {
        "count": 73950,
        "average": 0.4750236646382661
    },
    "754": {
        "count": 73499,
        "average": 0.47626498319705146
    },
    "755": {
        "count": 73549,
        "average": 0.4805639777563267
    },
    "756": {
        "count": 73247,
        "average": 0.48175351891545176
    },
    "757": {
        "count": 72705,
        "average": 0.4800082525273349
    },
    "758": {
        "count": 72597,
        "average": 0.4901166714878013
    },
    "759": {
        "count": 71965,
        "average": 0.48536093934551133
    },
    "760": {
        "count": 71946,
        "average": 0.4917299085425155
    },
    "761": {
        "count": 72046,
        "average": 0.49504483246814324
    },
    "762": {
        "count": 71303,
        "average": 0.4951685062339578
    },
    "763": {
        "count": 70805,
        "average": 0.501927829955511
    },
    "764": {
        "count": 70965,
        "average": 0.4959768900161975
    },
    "765": {
        "count": 70681,
        "average": 0.49946944723476067
    },
    "766": {
        "count": 70362,
        "average": 0.5039083596259413
    },
    "767": {
        "count": 70499,
        "average": 0.5043050256031991
    },
    "768": {
        "count": 69782,
        "average": 0.4997277234816924
    },
    "769": {
        "count": 69768,
        "average": 0.5115525742460736
    },
    "770": {
        "count": 69444,
        "average": 0.5049248315189263
    },
    "771": {
        "count": 69249,
        "average": 0.5118774278328853
    },
    "772": {
        "count": 69354,
        "average": 0.5157020503503777
    },
    "773": {
        "count": 68673,
        "average": 0.5109868507273622
    },
    "774": {
        "count": 68569,
        "average": 0.5099243098193056
    },
    "775": {
        "count": 68373,
        "average": 0.5210975092507267
    },
    "776": {
        "count": 68073,
        "average": 0.5228063990128232
    },
    "777": {
        "count": 67441,
        "average": 0.5231980545958659
    },
    "778": {
        "count": 67853,
        "average": 0.5241772655593666
    },
    "779": {
        "count": 67157,
        "average": 0.5235046234941981
    },
    "780": {
        "count": 66658,
        "average": 0.525758348585303
    },
    "781": {
        "count": 67250,
        "average": 0.5303494423791779
    },
    "782": {
        "count": 66579,
        "average": 0.5307529401162427
    },
    "783": {
        "count": 65975,
        "average": 0.5343387646835905
    },
    "784": {
        "count": 65759,
        "average": 0.5400477501178486
    },
    "785": {
        "count": 66213,
        "average": 0.5381571594701965
    },
    "786": {
        "count": 65624,
        "average": 0.5402901377544771
    },
    "787": {
        "count": 65723,
        "average": 0.5400392556639303
    },
    "788": {
        "count": 65524,
        "average": 0.5416641230694116
    },
    "789": {
        "count": 64787,
        "average": 0.5462361276181987
    },
    "790": {
        "count": 64408,
        "average": 0.5478201465656475
    },
    "791": {
        "count": 64316,
        "average": 0.5484482865849815
    },
    "792": {
        "count": 64022,
        "average": 0.5521851863421977
    },
    "793": {
        "count": 64127,
        "average": 0.5538228827171068
    },
    "794": {
        "count": 64192,
        "average": 0.5544616151545425
    },
    "795": {
        "count": 63763,
        "average": 0.5613757194611259
    },
    "796": {
        "count": 62881,
        "average": 0.5601851115599338
    },
    "797": {
        "count": 63052,
        "average": 0.5624563852058704
    },
    "798": {
        "count": 62202,
        "average": 0.561203819812865
    },
    "799": {
        "count": 62495,
        "average": 0.5610208816705328
    },
    "800": {
        "count": 61962,
        "average": 0.5672508957102697
    },
    "801": {
        "count": 62081,
        "average": 0.5693368341360487
    },
    "802": {
        "count": 61524,
        "average": 0.5648852480332914
    },
    "803": {
        "count": 61135,
        "average": 0.5685613805512374
    },
    "804": {
        "count": 60858,
        "average": 0.5719543856189839
    },
    "805": {
        "count": 61020,
        "average": 0.5789249426417483
    },
    "806": {
        "count": 60518,
        "average": 0.5727882613437333
    },
    "807": {
        "count": 59898,
        "average": 0.5803532672209383
    },
    "808": {
        "count": 60154,
        "average": 0.581341224191243
    },
    "809": {
        "count": 59883,
        "average": 0.5908020640248481
    },
    "810": {
        "count": 59544,
        "average": 0.5794370549509591
    },
    "811": {
        "count": 59645,
        "average": 0.5894039735099372
    },
    "812": {
        "count": 58833,
        "average": 0.5923036391141054
    },
    "813": {
        "count": 58672,
        "average": 0.5884578674665998
    },
    "814": {
        "count": 58647,
        "average": 0.589271403481852
    },
    "815": {
        "count": 58647,
        "average": 0.5930226610056831
    },
    "816": {
        "count": 57909,
        "average": 0.5960904177243637
    },
    "817": {
        "count": 57714,
        "average": 0.5995772256298294
    },
    "818": {
        "count": 57498,
        "average": 0.5989077880969761
    },
    "819": {
        "count": 57627,
        "average": 0.5992850573515864
    },
    "820": {
        "count": 57141,
        "average": 0.6015470502791442
    },
    "821": {
        "count": 57183,
        "average": 0.6095343021527357
    },
    "822": {
        "count": 56536,
        "average": 0.6125654450261814
    },
    "823": {
        "count": 56257,
        "average": 0.6063067707129792
    },
    "824": {
        "count": 56100,
        "average": 0.6111229946524082
    },
    "825": {
        "count": 55684,
        "average": 0.6115221607643146
    },
    "826": {
        "count": 54953,
        "average": 0.6135606791258014
    },
    "827": {
        "count": 55591,
        "average": 0.6153693943264192
    },
    "828": {
        "count": 55359,
        "average": 0.6178399176285697
    },
    "829": {
        "count": 54786,
        "average": 0.6170189464461632
    },
    "830": {
        "count": 54767,
        "average": 0.6264538864644756
    },
    "831": {
        "count": 54425,
        "average": 0.626090950849795
    },
    "832": {
        "count": 53748,
        "average": 0.6281908164024754
    },
    "833": {
        "count": 53612,
        "average": 0.6254942923226113
    },
    "834": {
        "count": 53100,
        "average": 0.6300188323917122
    },
    "835": {
        "count": 52942,
        "average": 0.6292168788485496
    },
    "836": {
        "count": 53243,
        "average": 0.6353699077813095
    },
    "837": {
        "count": 52844,
        "average": 0.6377261373098232
    },
    "838": {
        "count": 52487,
        "average": 0.6388057995313083
    },
    "839": {
        "count": 51906,
        "average": 0.6388856779563011
    },
    "840": {
        "count": 51783,
        "average": 0.6449800127454999
    },
    "841": {
        "count": 51933,
        "average": 0.6396510889030139
    },
    "842": {
        "count": 51190,
        "average": 0.6475483492869691
    },
    "843": {
        "count": 51067,
        "average": 0.6487359743082577
    },
    "844": {
        "count": 51094,
        "average": 0.6471601362195175
    },
    "845": {
        "count": 50938,
        "average": 0.6516942164984749
    },
    "846": {
        "count": 50485,
        "average": 0.6536000792314579
    },
    "847": {
        "count": 50097,
        "average": 0.6527536579036697
    },
    "848": {
        "count": 49872,
        "average": 0.6545556624959882
    },
    "849": {
        "count": 49716,
        "average": 0.6617990184246467
    },
    "850": {
        "count": 49234,
        "average": 0.6627127594751535
    },
    "851": {
        "count": 48788,
        "average": 0.6654095269328483
    },
    "852": {
        "count": 49055,
        "average": 0.6614412394251339
    },
    "853": {
        "count": 48457,
        "average": 0.6663433559650921
    },
    "854": {
        "count": 48410,
        "average": 0.669778971286931
    },
    "855": {
        "count": 47848,
        "average": 0.6699548570473177
    },
    "856": {
        "count": 47875,
        "average": 0.6747780678851123
    },
    "857": {
        "count": 47442,
        "average": 0.6770793811390834
    },
    "858": {
        "count": 47432,
        "average": 0.6786979254511774
    },
    "859": {
        "count": 46685,
        "average": 0.673599657277498
    },
    "860": {
        "count": 46672,
        "average": 0.6793794994857677
    },
    "861": {
        "count": 46141,
        "average": 0.679850891831561
    },
    "862": {
        "count": 46213,
        "average": 0.6844178045138795
    },
    "863": {
        "count": 46208,
        "average": 0.6855955678670344
    },
    "864": {
        "count": 45759,
        "average": 0.6881050722262262
    },
    "865": {
        "count": 45633,
        "average": 0.6875068481142991
    },
    "866": {
        "count": 45290,
        "average": 0.6924707440936195
    },
    "867": {
        "count": 44901,
        "average": 0.6906973118638687
    },
    "868": {
        "count": 44694,
        "average": 0.6964245760057344
    },
    "869": {
        "count": 44566,
        "average": 0.7003096530987826
    },
    "870": {
        "count": 43954,
        "average": 0.6972289211448375
    },
    "871": {
        "count": 43517,
        "average": 0.6980949973573491
    },
    "872": {
        "count": 43453,
        "average": 0.6965917197891963
    },
    "873": {
        "count": 43217,
        "average": 0.7057639354883491
    },
    "874": {
        "count": 43214,
        "average": 0.7068079788957359
    },
    "875": {
        "count": 42891,
        "average": 0.7003100883635279
    },
    "876": {
        "count": 42673,
        "average": 0.7068403908794826
    },
    "877": {
        "count": 42612,
        "average": 0.7086736130667388
    },
    "878": {
        "count": 42538,
        "average": 0.7118341247825486
    },
    "879": {
        "count": 42194,
        "average": 0.7127553680618137
    },
    "880": {
        "count": 41432,
        "average": 0.7233539293299819
    },
    "881": {
        "count": 41600,
        "average": 0.7230288461538537
    },
    "882": {
        "count": 41056,
        "average": 0.7195050662509819
    },
    "883": {
        "count": 40919,
        "average": 0.7245289474327293
    },
    "884": {
        "count": 40854,
        "average": 0.7222303813580103
    },
    "885": {
        "count": 40509,
        "average": 0.7187291712952689
    },
    "886": {
        "count": 40039,
        "average": 0.7233197632308497
    },
    "887": {
        "count": 39571,
        "average": 0.7323292310024953
    },
    "888": {
        "count": 39528,
        "average": 0.7345679012345746
    },
    "889": {
        "count": 39222,
        "average": 0.7363214522461915
    },
    "890": {
        "count": 39199,
        "average": 0.7349422179137182
    },
    "891": {
        "count": 38963,
        "average": 0.7367245848625597
    },
    "892": {
        "count": 38512,
        "average": 0.7431969256335615
    },
    "893": {
        "count": 38249,
        "average": 0.7403330806034114
    },
    "894": {
        "count": 37969,
        "average": 0.7387342305565124
    },
    "895": {
        "count": 37578,
        "average": 0.7474053967747118
    },
    "896": {
        "count": 37285,
        "average": 0.7464395869652672
    },
    "897": {
        "count": 37252,
        "average": 0.7435842370879459
    },
    "898": {
        "count": 37098,
        "average": 0.7467248908296977
    },
    "899": {
        "count": 37015,
        "average": 0.7528029177360558
    },
    "900": {
        "count": 36608,
        "average": 0.7544252622377658
    },
    "901": {
        "count": 36173,
        "average": 0.7560611505819265
    },
    "902": {
        "count": 35713,
        "average": 0.751743062750261
    },
    "903": {
        "count": 35956,
        "average": 0.7593725664701261
    },
    "904": {
        "count": 35438,
        "average": 0.7610474631751268
    },
    "905": {
        "count": 35068,
        "average": 0.7643435610813235
    },
    "906": {
        "count": 35068,
        "average": 0.7691912855024531
    },
    "907": {
        "count": 34141,
        "average": 0.7686066606133359
    },
    "908": {
        "count": 34416,
        "average": 0.7756857275685679
    },
    "909": {
        "count": 33843,
        "average": 0.7732470525662544
    },
    "910": {
        "count": 33477,
        "average": 0.7756071332556685
    },
    "911": {
        "count": 33026,
        "average": 0.7839278144492234
    },
    "912": {
        "count": 32940,
        "average": 0.7795385549483933
    },
    "913": {
        "count": 32729,
        "average": 0.782089278621411
    },
    "914": {
        "count": 32327,
        "average": 0.7827821944504563
    },
    "915": {
        "count": 32175,
        "average": 0.7884071484071495
    },
    "916": {
        "count": 31781,
        "average": 0.7825115635127875
    },
    "917": {
        "count": 31173,
        "average": 0.7878292111763405
    },
    "918": {
        "count": 31144,
        "average": 0.7898792704854825
    },
    "919": {
        "count": 30971,
        "average": 0.7910303186852218
    },
    "920": {
        "count": 30678,
        "average": 0.7973792294152122
    },
    "921": {
        "count": 30390,
        "average": 0.7969068772622543
    },
    "922": {
        "count": 30179,
        "average": 0.8082110076543335
    },
    "923": {
        "count": 29810,
        "average": 0.7999329084199951
    },
    "924": {
        "count": 29448,
        "average": 0.7989676718283082
    },
    "925": {
        "count": 29264,
        "average": 0.80016402405686
    },
    "926": {
        "count": 29176,
        "average": 0.8055936386070741
    },
    "927": {
        "count": 28864,
        "average": 0.8052937915742792
    },
    "928": {
        "count": 28548,
        "average": 0.8086731119517996
    },
    "929": {
        "count": 28277,
        "average": 0.8160342327686803
    },
    "930": {
        "count": 27965,
        "average": 0.8130520293223664
    },
    "931": {
        "count": 27822,
        "average": 0.8170512544029922
    },
    "932": {
        "count": 27430,
        "average": 0.8204885162231126
    },
    "933": {
        "count": 27425,
        "average": 0.818632634457612
    },
    "934": {
        "count": 26630,
        "average": 0.8175741644761534
    },
    "935": {
        "count": 26706,
        "average": 0.8192166554332356
    },
    "936": {
        "count": 26305,
        "average": 0.8261167078502194
    },
    "937": {
        "count": 26120,
        "average": 0.8314701378254176
    },
    "938": {
        "count": 25968,
        "average": 0.8284041897720191
    },
    "939": {
        "count": 25349,
        "average": 0.8295790760976771
    },
    "940": {
        "count": 25112,
        "average": 0.8271742593182551
    },
    "941": {
        "count": 25258,
        "average": 0.8371209121862393
    },
    "942": {
        "count": 24549,
        "average": 0.8349423601776055
    },
    "943": {
        "count": 24515,
        "average": 0.8311238017540288
    },
    "944": {
        "count": 24089,
        "average": 0.8443272863132573
    },
    "945": {
        "count": 23687,
        "average": 0.8479334656140467
    },
    "946": {
        "count": 23737,
        "average": 0.843956692084091
    },
    "947": {
        "count": 23418,
        "average": 0.8482363993509238
    },
    "948": {
        "count": 23245,
        "average": 0.8452140245214018
    },
    "949": {
        "count": 23098,
        "average": 0.8402459087366866
    },
    "950": {
        "count": 22779,
        "average": 0.8540761227446344
    },
    "951": {
        "count": 22550,
        "average": 0.8483370288248353
    },
    "952": {
        "count": 22330,
        "average": 0.8577698163905079
    },
    "953": {
        "count": 21758,
        "average": 0.8517326960198592
    },
    "954": {
        "count": 21641,
        "average": 0.8561064645811202
    },
    "955": {
        "count": 21573,
        "average": 0.8608445742363178
    },
    "956": {
        "count": 21446,
        "average": 0.8545183250955909
    },
    "957": {
        "count": 20927,
        "average": 0.8570268074736044
    },
    "958": {
        "count": 20750,
        "average": 0.8639036144578326
    },
    "959": {
        "count": 20637,
        "average": 0.8693608567136681
    },
    "960": {
        "count": 20153,
        "average": 0.8643378157098224
    },
    "961": {
        "count": 20159,
        "average": 0.8644774046331664
    },
    "962": {
        "count": 19945,
        "average": 0.8710453747806467
    },
    "963": {
        "count": 19763,
        "average": 0.8744117795881228
    },
    "964": {
        "count": 19672,
        "average": 0.875152501016673
    },
    "965": {
        "count": 19266,
        "average": 0.8748053565867346
    },
    "966": {
        "count": 18766,
        "average": 0.8771181924757526
    },
    "967": {
        "count": 18839,
        "average": 0.8716492382822842
    },
    "968": {
        "count": 18695,
        "average": 0.8846750468039589
    },
    "969": {
        "count": 18307,
        "average": 0.8749112361391826
    },
    "970": {
        "count": 17989,
        "average": 0.8775918616932572
    },
    "971": {
        "count": 17731,
        "average": 0.8813377700073346
    },
    "972": {
        "count": 17361,
        "average": 0.8839928575542891
    },
    "973": {
        "count": 17467,
        "average": 0.8763382378198865
    },
    "974": {
        "count": 17073,
        "average": 0.8843788437884371
    },
    "975": {
        "count": 17002,
        "average": 0.8910716386307509
    },
    "976": {
        "count": 16636,
        "average": 0.8926424621303176
    },
    "977": {
        "count": 16408,
        "average": 0.8882252559726949
    },
    "978": {
        "count": 16339,
        "average": 0.8887324805679664
    },
    "979": {
        "count": 16099,
        "average": 0.8885645071122461
    },
    "980": {
        "count": 15698,
        "average": 0.8968021404000502
    },
    "981": {
        "count": 15593,
        "average": 0.8948246007824016
    },
    "982": {
        "count": 15283,
        "average": 0.8972714781129395
    },
    "983": {
        "count": 15252,
        "average": 0.9012588512981894
    },
    "984": {
        "count": 15002,
        "average": 0.9033462205039371
    },
    "985": {
        "count": 14870,
        "average": 0.9024882313382645
    },
    "986": {
        "count": 14532,
        "average": 0.9098541150564299
    },
    "987": {
        "count": 14399,
        "average": 0.909021459823602
    },
    "988": {
        "count": 14265,
        "average": 0.9104100946372221
    },
    "989": {
        "count": 13969,
        "average": 0.9080821819743695
    },
    "990": {
        "count": 13989,
        "average": 0.9053542068768349
    },
    "991": {
        "count": 13752,
        "average": 0.9109947643979079
    },
    "992": {
        "count": 13314,
        "average": 0.9121225777377201
    },
    "993": {
        "count": 13366,
        "average": 0.9102199610953157
    },
    "994": {
        "count": 13103,
        "average": 0.9102495611692004
    },
    "995": {
        "count": 12862,
        "average": 0.9132327787280352
    },
    "996": {
        "count": 12674,
        "average": 0.9181000473410152
    },
    "997": {
        "count": 12374,
        "average": 0.9167609503798341
    },
    "998": {
        "count": 12262,
        "average": 0.9204045017126066
    },
    "999": {
        "count": 12099,
        "average": 0.9213158112240669
    },
    "1000": {
        "count": 0,
        "average": 0
    }
}